prince_cr/__init__.py
prince_cr/config.py
prince_cr/core.py
prince_cr/cosmology.py
prince_cr/cr_sources.py
prince_cr/data.py
prince_cr/decays.py
prince_cr/interaction_rates.py
prince_cr/photonfields.py
prince_cr/util.py
prince_cr/version.py
prince_cr/cross_sections/__init__.py
prince_cr/cross_sections/_phenom_relations.py
prince_cr/cross_sections/base.py
prince_cr/cross_sections/disintegration.py
prince_cr/cross_sections/photo_meson.py
prince_cr/cross_sections/response.py
prince_cr/data/particle_data.ppo
prince_cr/solvers/__init__.py
prince_cr/solvers/mkl_interface.py
prince_cr/solvers/partial_diff.py
prince_cr/solvers/propagation.py
prince_cr/tests/test_csec.py
prince_cr/tests/test_intrates.py
prince_cr/tests/test_propagation.py
prince_cr-0.6.0.dist-info/LICENSE
prince_cr-0.6.0.dist-info/METADATA
prince_cr-0.6.0.dist-info/WHEEL
prince_cr-0.6.0.dist-info/top_level.txt
prince_cr-0.6.0.dist-info/RECORD
