Metadata-Version: 2.1
Name: prince-cr
Version: 0.6.0
Summary: Cosmic ray PRopagation Including Nuclear Cascade equations
Home-page: https://github.com/joheinze/PriNCe
Author: Jonas Heinze and Anatoli Fedynitch
Author-email: afedynitch@gmail.com
License: BSD 3-Clause License
Platform: UNKNOWN
Classifier: Programming Language :: Python
Classifier: Programming Language :: Python :: 3
Classifier: Programming Language :: Python :: 3.6
Classifier: Programming Language :: Python :: 3.7
Classifier: Programming Language :: Python :: 3.8
Classifier: Topic :: Scientific/Engineering :: Physics
Classifier: Intended Audience :: Science/Research
Classifier: Development Status :: 4 - Beta
Classifier: License :: OSI Approved :: BSD License
Requires-Dist: scipy
Requires-Dist: numpy
Requires-Dist: tqdm
Requires-Dist: h5py
Requires-Dist: requests
